transparency_epias/__init__.py
transparency_epias/consumption/__init__.py
transparency_epias/consumption/consumptionClient.py
transparency_epias/gas/__init__.py
transparency_epias/gas/gasTraClients.py
transparency_epias/markets/__init__.py
transparency_epias/markets/ancillaryServiceClient.py
transparency_epias/markets/balancingPowerClient.py
transparency_epias/markets/dayaheadClient.py
transparency_epias/markets/intradayClient.py
transparency_epias/markets/validate.py
transparency_epias/production/__init__.py
transparency_epias/production/productionClient.py
transparency_epias/tools/__init__.py
transparency_epias/tools/reportClient.py
transparencyEpias-0.0.1.dist-info/LICENSE
transparencyEpias-0.0.1.dist-info/METADATA
transparencyEpias-0.0.1.dist-info/WHEEL
transparencyEpias-0.0.1.dist-info/top_level.txt
transparencyEpias-0.0.1.dist-info/RECORD
