Metadata-Version: 2.1
Name: transparencyEpias
Version: 0.0.1
Summary: ackage for EPIAS (Turkish Electricity Market Operating Company) Transparency API Service
Home-page: https://github.com/ErenEla/transparencyEpias
Author: Eren Ela
Author-email: ela.eren1@gmail.com
License: UNKNOWN
Platform: UNKNOWN
Classifier: Programming Language :: Python :: 3
Classifier: License :: OSI Approved :: MIT License
Classifier: Operating System :: OS Independent
Requires-Python: >=3
